{
	"format_version": "1.12.0",
	"minecraft:geometry": [
		{
			"description": {
				"identifier": "geometry.cheetah",
				"texture_width": 64,
				"texture_height": 32,
				"visible_bounds_width": 6,
				"visible_bounds_height": 2,
				"visible_bounds_offset": [0, 1, 0]
			},
			"bones": [
				{
					"name": "body",
					"pivot": [0, 11, 1],
					"cubes": [
						{
							"origin": [-3.22, -1.88, -3.83],
							"size": [6.44, 25.76, 9.66],
							"pivot": [0, 11, 1],
							"rotation": [90, 0, 0],
							"uv": {
								"north": {"uv": [26, 6], "uv_size": [4, 16]},
								"east": {"uv": [20, 6], "uv_size": [6, 16]},
								"south": {"uv": [36, 6], "uv_size": [4, 16]},
								"west": {"uv": [30, 6], "uv_size": [6, 16]},
								"up": {"uv": [26, 0], "uv_size": [4, 6]},
								"down": {"uv": [30, 6], "uv_size": [4, -6]}
							}
						}
					]
				},
				{
					"name": "head",
					"parent": "body",
					"pivot": [0, 18.49, -14.49],
					"cubes": [
						{
							"origin": [-4.025, 11, -19.93],
							"size": [8.05, 6.44, 8.05],
							"uv": {
								"north": {"uv": [5, 5], "uv_size": [5, 4]},
								"east": {"uv": [0, 5], "uv_size": [5, 4]},
								"south": {"uv": [15, 5], "uv_size": [5, 4]},
								"west": {"uv": [10, 5], "uv_size": [5, 4]},
								"up": {"uv": [5, 0], "uv_size": [5, 5]},
								"down": {"uv": [10, 5], "uv_size": [5, -5]}
							}
						},
						{
							"origin": [-2.415, 11.02515, -21.54],
							"size": [4.83, 3.22, 3.22],
							"uv": {
								"north": {"uv": [2, 26], "uv_size": [3, 2]},
								"east": {"uv": [0, 26], "uv_size": [2, 2]},
								"south": {"uv": [7, 26], "uv_size": [3, 2]},
								"west": {"uv": [5, 26], "uv_size": [2, 2]},
								"up": {"uv": [2, 24], "uv_size": [3, 2]},
								"down": {"uv": [5, 26], "uv_size": [3, -2]}
							}
						},
						{
							"origin": [-3.22, 17.44, -15.1],
							"size": [1.61, 1.61, 3.22],
							"uv": {
								"north": {"uv": [2, 12], "uv_size": [1, 1]},
								"east": {"uv": [0, 12], "uv_size": [2, 1]},
								"south": {"uv": [5, 12], "uv_size": [1, 1]},
								"west": {"uv": [3, 12], "uv_size": [2, 1]},
								"up": {"uv": [2, 10], "uv_size": [1, 2]},
								"down": {"uv": [3, 12], "uv_size": [1, -2]}
							}
						},
						{
							"origin": [1.61, 17.44, -15.1],
							"size": [1.61, 1.61, 3.22],
							"uv": {
								"north": {"uv": [8, 12], "uv_size": [1, 1]},
								"east": {"uv": [6, 12], "uv_size": [2, 1]},
								"south": {"uv": [11, 12], "uv_size": [1, 1]},
								"west": {"uv": [9, 12], "uv_size": [2, 1]},
								"up": {"uv": [8, 10], "uv_size": [1, 2]},
								"down": {"uv": [9, 12], "uv_size": [1, -2]}
							}
						}
					],
					"locators": {
						"lead": [0, 14.22, -15.1]
					}
				},
				{
					"name": "tail1",
					"parent": "body",
					"pivot": [0, 18.49, 12.88],
					"cubes": [
						{
							"origin": [-0.805, 1.34, 12.27],
							"size": [1.61, 12.88, 1.61],
							"pivot": [0, 14.22, 12.27],
							"rotation": [52.5, 0, 0],
							"uv": {
								"north": {"uv": [1, 16], "uv_size": [1, 8]},
								"east": {"uv": [0, 16], "uv_size": [1, 8]},
								"south": {"uv": [3, 16], "uv_size": [1, 8]},
								"west": {"uv": [2, 16], "uv_size": [1, 8]},
								"up": {"uv": [1, 15], "uv_size": [1, 1]},
								"down": {"uv": [2, 16], "uv_size": [1, -1]}
							}
						}
					]
				},
				{
					"name": "tail2",
					"parent": "tail1",
					"pivot": [0, 10.64125, 23.1035],
					"cubes": [
						{
							"origin": [-0.805, -6.50875, 22.4935],
							"size": [1.61, 12.88, 1.61],
							"pivot": [0, 6.37125, 22.4935],
							"rotation": [90, 0, 0],
							"uv": {
								"north": {"uv": [5, 16], "uv_size": [1, 8]},
								"east": {"uv": [4, 16], "uv_size": [1, 8]},
								"south": {"uv": [7, 16], "uv_size": [1, 8]},
								"west": {"uv": [6, 16], "uv_size": [1, 8]},
								"up": {"uv": [5, 15], "uv_size": [1, 1]},
								"down": {"uv": [6, 16], "uv_size": [1, -1]}
							}
						}
					]
				},
				{
					"name": "backLegL",
					"parent": "body",
					"pivot": [1.771, 13.66, 11.27],
					"cubes": [
						{
							"origin": [0.161, -0.27, 9.05],
							"size": [3.22, 9.66, 3.22],
							"uv": {
								"north": {"uv": [10, 15], "uv_size": [2, 6]},
								"east": {"uv": [8, 15], "uv_size": [2, 6]},
								"south": {"uv": [14, 15], "uv_size": [2, 6]},
								"west": {"uv": [12, 15], "uv_size": [2, 6]},
								"up": {"uv": [10, 13], "uv_size": [2, 2]},
								"down": {"uv": [12, 15], "uv_size": [2, -2]}
							}
						}
					]
				},
				{
					"name": "backLegR",
					"parent": "body",
					"pivot": [-1.771, 13.66, 11.27],
					"cubes": [
						{
							"origin": [-3.381, -0.27, 9.05],
							"size": [3.22, 9.66, 3.22],
							"uv": {
								"north": {"uv": [10, 15], "uv_size": [2, 6]},
								"east": {"uv": [8, 15], "uv_size": [2, 6]},
								"south": {"uv": [14, 15], "uv_size": [2, 6]},
								"west": {"uv": [12, 15], "uv_size": [2, 6]},
								"up": {"uv": [10, 13], "uv_size": [2, 2]},
								"down": {"uv": [12, 15], "uv_size": [2, -2]}
							}
						}
					]
				},
				{
					"name": "frontLegL",
					"parent": "body",
					"pivot": [1.932, 20.1, -6.44],
					"cubes": [
						{
							"origin": [0.322, 0.052, -8.66],
							"size": [3.22, 16.1, 3.22],
							"uv": {
								"north": {"uv": [42, 2], "uv_size": [2, 10]},
								"east": {"uv": [40, 2], "uv_size": [2, 10]},
								"south": {"uv": [46, 2], "uv_size": [2, 10]},
								"west": {"uv": [44, 2], "uv_size": [2, 10]},
								"up": {"uv": [42, 0], "uv_size": [2, 2]},
								"down": {"uv": [44, 2], "uv_size": [2, -2]}
							}
						}
					]
				},
				{
					"name": "frontLegR",
					"parent": "body",
					"pivot": [-1.932, 20.1, -6.44],
					"cubes": [
						{
							"origin": [-3.542, 0.052, -8.66],
							"size": [3.22, 16.1, 3.22],
							"uv": {
								"north": {"uv": [42, 2], "uv_size": [2, 10]},
								"east": {"uv": [40, 2], "uv_size": [2, 10]},
								"south": {"uv": [46, 2], "uv_size": [2, 10]},
								"west": {"uv": [44, 2], "uv_size": [2, 10]},
								"up": {"uv": [42, 0], "uv_size": [2, 2]},
								"down": {"uv": [44, 2], "uv_size": [2, -2]}
							}
						}
					]
				}
			]
		}
	]
}